Workbook

Sheet Légende
A1: QuickOrder — cas de test
A2: Carnet de campagne de Samy. Rédigé avant d'avoir ouvert l'appli.
A4: Cellules jaunes | B4: À remplir pendant l'exécution (résultat obtenu, statut, preuve, bug lié, date/testeur).
A5: Statuts | B5: À exécuter / Pass / Fail / Blocked / Skipped (liste déroulante). Un Blocked ou Skipped doit être justifié dans « Résultat obtenu ».
A6: [à confirmer] | B6: Donnée ou règle que je ne connais pas encore : à vérifier dans Swagger ou la doc de lancement, puis à corriger.
A7: Résultats attendus | B7: Écrits avant d'avoir vu l'appli, d'après la logique d'une app de livraison. Ils se corrigent si la spec dit autre chose.
A8: Colonne Risque | B8: Renvoie à risk-matrix.md (R1 à R12).
A9: Synthèse | B9: Les chiffres se calculent seuls à partir de la colonne Statut. Rien à saisir sauf les deux cellules bleues du verdict.
A11: Exemple de ligne remplie (format attendu — ce n'est PAS un cas réel)
A12: ID | B12: Résultat obtenu | C12: Statut | D12: Preuve | E12: Bug lié | F12: Date / testeur
A13: EXEMPLE-00 | B13: Total affiché 12,40 € au lieu de 12,41 € attendu (arrondi perdu) | C13: Fail | D13: evidence/BUG-001/total.png | E13: BUG-001 | F13: 12/10/2026 — Samy

Sheet Cas de test
A1: ID | B1: Catégorie | C1: Canal | D1: Titre | E1: Objectif | F1: Préconditions | G1: Données | H1: Étapes | I1: Résultat attendu | J1: Risque | K1: Résultat obtenu | L1: Statut | M1: Preuve | N1: Bug lié | O1: Date / testeur
A2: NOM-01 | B2: Nominal | C2: UI | D2: Connexion avec un compte client valide | E2: Vérifier qu'un client existant peut se connecter | F2: Appli lancée (base seedée) ; http://127.0.0.1:5000 accessible | G2: alice@example.com / Password123! | H2: 1. Ouvrir http://127.0.0.1:5000 2. Aller à la connexion 3. Saisir les identifiants 4. Valider | I2: Accès à l'espace connecté, identité visible, aucune erreur rouge en console DevTools | J2: R5 | L2: Skipped | O2: 12/10/2026 — Samy
A3: NOM-02 | B3: Nominal | C3: UI | D3: Parcourir les restaurants et ouvrir un menu | E3: Vérifier la consultation du catalogue | F3: Appli lancée ; connecté ou non (noter les deux) | G3: Premier restaurant de la liste | H3: 1. Ouvrir la liste des restaurants 2. Cliquer sur un restaurant 3. Lire le menu 4. Onglet Network : relever les codes HTTP | I3: Liste et menu affichés avec noms et prix lisibles ; pas de requête en 4xx/5xx | J3: R12 | K3: PARTIEL. Liste de 6 restaurants affichée, console DevTools vide. Menu non ouvert, onglet Network non relevé. Non terminé : pas de Pass. | L3: Skipped | O3: 12/10/2026 — Samy
A4: NOM-03 | B4: Nominal | C4: UI | D4: Ajouter deux produits au panier : le total est juste | E4: Vérifier le calcul du sous-total | F4: Connecté en alice ; restaurant ouvert | G4: 2 produits différents, quantité 1 chacun | H4: 1. Ajouter produit A 2. Ajouter produit B 3. Ouvrir le panier 4. Comparer le total à la somme des prix du menu (calcul à la main) | I4: Sous-total = prix A + prix B ; frais et réductions éventuels affichés séparément | J4: R1 | L4: Skipped | O4: 12/10/2026 — Samy
A5: NOM-04 | B5: Nominal | C5: UI | D5: Passer une commande complète (checkout) | E5: Valider le parcours critique P1 de bout en bout | F5: Connecté en alice ; panier au-dessus du minimum de commande | G5: Paiement carte (payment_method = card) | H5: 1. Ouvrir le panier 2. Lancer le checkout 3. Choisir carte 4. Valider 5. Lire la confirmation | I5: Confirmation avec numéro et montant ; commande visible dans l'historique ; stock du produit diminué si géré | J5: R3 | L5: Skipped | O5: 12/10/2026 — Samy
A6: NOM-05 | B6: Nominal | C6: API | D6: Health puis liste des restaurants | E6: Vérifier un GET public et un GET authentifié | F6: Swagger (/docs/) ou collection Postman importée ; clé quickorder-demo-key | G6: GET /api/health (sans clé) ; GET /api/restaurants ; GET /api/restaurants/1 ; GET /api/restaurants?q=pizza&min_rating=4 ; GET /api/restaurants?category=<une catégorie vue dans la liste> | H6: 1. GET /api/health sans clé 2. GET /api/restaurants avec X-API-Key 3. GET /api/restaurants/1 4. Rejouer la liste avec q, min_rating puis category 5. Vérifier que chaque résultat respecte le filtre | I6: Health : 200 sans clé. Liste et détail : 200, JSON avec id, name, category, delivery_fee, minimum_order, delivery_time_min, rating, is_open. Filtres respectés (note ≥ 4, nom/catégorie correspondants) | J6: R2 | K6: PARTIEL. GET /health sans clé : 200 (status ok). GET /restaurants avec clé : JSON, count 6, champs conformes à OpenAPI. GET /restaurants/1 : Burger Factory, identique à la liste. Filtres q, min_rating, category non testés. Non terminé : pas de Pass. | L6: Skipped | O6: 12/10/2026 — Samy
A7: NOM-06 | B7: Nominal | C7: API | D7: Créer une commande puis la relire (API ↔ UI) | E7: Vérifier POST /orders, GET /orders/{id} et la cohérence avec l'UI | F7: Clé API (compte API = alice) ; product_id 1 existe et est en stock | G7: POST /api/orders {"items":[{"product_id":1,"quantity":1}],"payment_method":"card"} | H7: 1. POST /orders 2. Noter l'id renvoyé 3. GET /orders/{id} 4. GET /orders (liste) 5. Se connecter en alice dans l'UI et retrouver la commande | I7: 201 avec id de commande (code documenté dans OpenAPI) ; GET /orders/{id} renvoie les mêmes données ; la commande est dans GET /orders et dans l'UI avec les mêmes montants | J7: R9 | L7: Skipped | O7: 12/10/2026 — Samy
A8: LIM-01 | B8: Limite | C8: API | D8: Quantité 0, 1 et négative | E8: Vérifier la borne basse de quantité (OpenAPI : minimum 1) | F8: Clé API configurée ; produit en stock | G8: quantity : 1, 0, -1, -100 | H8: 1. POST /orders avec quantity = 1 2. Idem avec 0 3. Idem avec -1 4. Idem avec -100 5. Vérifier aussi dans l'UI (champ quantité du panier) | I8: 1 accepté (201) ; 0, -1 et -100 refusés (400 attendu) avec message ; aucun total négatif ni commande créée | J8: R7 | L8: Skipped | O8: 12/10/2026 — Samy
A9: LIM-02 | B9: Limite | C9: API | D9: Quantité maximale (20 d'après OpenAPI) et stock | E9: Vérifier la borne haute de quantité et la gestion du stock | F9: Un produit au stock connu (GET /api/products/{id}) ; un produit indisponible si existant [à relever] | G9: quantity = 20, 21, 100, 1000, 1.5 ; quantity = stock, stock+1 ; produit indisponible | H9: 1. POST /orders avec quantity = 20, puis 21 2. Idem avec 1.5 et "abc" 3. Lire le stock du produit, commander stock puis stock+1 4. Commander un produit indisponible 5. Relire le stock après chaque commande | I9: 20 accepté ; 21 et au-delà refusés (400) ; décimal refusé ; stock insuffisant ou produit indisponible refusé (409 d'après OpenAPI) ; stock jamais négatif | J9: R8 | L9: Skipped | O9: 12/10/2026 — Samy
A10: LIM-03 | B10: Limite | C10: UI+API | D10: Minimum de commande : seuil −0,01 / seuil / +0,01 | E10: Vérifier l'absence d'erreur d'une unité à la borne | F10: minimum_order du restaurant lu via GET /api/restaurants | G10: Paniers dont le sous-total vaut minimum_order −0,01, minimum_order, +0,01 (ajuster produits / quantités) | H10: 1. Construire chaque panier 2. Tenter de commander (UI puis API) 3. Comparer UI et API | I10: Refus sous le minimum avec message (code à noter : 400 attendu, non documenté dans OpenAPI) ; acceptation à partir du minimum (règle « ≥ » à vérifier) ; UI et API cohérentes | J10: R10 | L10: Skipped | O10: 12/10/2026 — Samy
A11: LIM-04 | B11: Limite | C11: API | D11: Coupon : bornes du subtotal, minimum et plafond de réduction | E11: Vérifier les bornes de /coupons/validate, un subtotal trafiqué et le plafond de réduction | F11: Clé API ; coupon WELCOME10 (pourcentage, minimum et plafond à relever dans les réponses ou l'UI) | G11: POST /api/coupons/validate {"code":"WELCOME10","subtotal": X} avec X = 0, -5, 0.01, minimum−0.01, minimum, 32.50, 100, 999999, "abc" | H11: 1. Envoyer chaque valeur de subtotal 2. Noter code HTTP, corps et réduction calculée 3. Comparer avec un calcul manuel (pourcentage puis plafond) | I11: OpenAPI : subtotal ≥ 0. Négatif et texte refusés ; sous le minimum : refus clair ; réduction exacte aux bornes ; plafonnée pour un gros subtotal ; jamais supérieure au subtotal ; pas de 500 | J11: R4 | L11: Skipped | O11: 12/10/2026 — Samy
A12: LIM-05 | B12: Limite | C12: UI+API | D12: Arrondi du total avec prix décimaux | E12: Vérifier que le centime ne se perd pas | F12: Connecté ; produits à prix décimaux | G12: 3 produits à prix décimaux ; avec et sans WELCOME10 | H12: 1. Ajouter les produits 2. Calculer le total à la main (sous-total, réduction, frais) 3. Comparer panier, confirmation, historique, GET /orders/{id} | I12: Même total, arrondi cohérent au centime, aux quatre endroits | J12: R1 | L12: Skipped | O12: 12/10/2026 — Samy
A13: LIM-06 | B13: Limite | C13: API | D13: Paiement cash : montant reçu aux bornes ; PayPal | E13: Vérifier la règle du montant reçu en espèces et observer PayPal | F13: Clé API ; total d'une commande connu | G13: payment_method = cash avec cash_received = total−0.01, total, total+0.01, 0, -5, 1, absent ; payment_method = paypal ; payment_method = bitcoin | H13: 1. POST /orders avec payment_method = cash et chaque valeur de cash_received 2. POST /orders avec payment_method = paypal 3. Noter code HTTP, message, et si une commande est créée | I13: cash_received < total ou absent : refus (400 attendu) ; ≥ total accepté, rendu de monnaie correct s'il existe ; paypal : comportement à relever et à comparer à la doc ; méthode hors enum (card, paypal, cash) refusée | J13: R3 | L13: Skipped | O13: 12/10/2026 — Samy
A14: ERR-01 | B14: Erreur | C14: UI | D14: Connexion avec mauvais mot de passe / compte inexistant | E14: Vérifier le message et l'absence de fuite d'information | F14: Compte alice connu | G14: alice@example.com + mauvais mot de passe ; inconnu@example.com + n'importe quoi | H14: 1. Saisir alice + mauvais mot de passe 2. Saisir un compte inexistant 3. Comparer les messages | I14: Refus ; message identique et non technique dans les deux cas ; aucune session ouverte | J14: R5 | L14: Skipped | O14: 12/10/2026 — Samy
A15: ERR-02 | B15: Erreur | C15: API | D15: API sans clé, clé vide ou clé fausse | E15: Vérifier la protection de l'API | F15: Endpoints connus | G15: GET /api/restaurants, GET /api/orders, POST /api/orders sans X-API-Key ; clé vide ; clé fausse | H15: 1. Rejouer chaque appel sans clé (Postman/Bruno, ou Swagger sans Authorize) 2. Clé vide 3. Clé fausse (ex. quickorder-demo-keyX) | I15: 401 ou 403, corps JSON explicite, aucune donnée renvoyée ; /api/health reste accessible (à confirmer) | J15: R2 | L15: Skipped | O15: 12/10/2026 — Samy
A16: ERR-03 | B16: Erreur | C16: API | D16: Identifiants inexistants ou mal formés | E16: Vérifier la gestion des ressources absentes | F16: Clé API configurée | G16: /api/restaurants/999999 ; /api/products/999999 ; /api/restaurants/999999/products ; /api/orders/999999 ; ids -1 et abc | H16: 1. Appeler chaque URL 2. Relever code HTTP et corps | I16: 404 attendu pour une ressource inexistante (OpenAPI le documente seulement pour /restaurants/{id}) ; relever ce que renvoient les autres routes ; JSON propre et homogène, aucune trace technique | J16: R5 | K16: PARTIEL. GET /restaurants/999 : « not found » (code HTTP à confirmer). /products/999, /restaurants/999/products, /orders/999 non testés. Non terminé. | L16: Skipped | O16: 12/10/2026 — Samy
A17: ERR-04 | B17: Erreur | C17: API | D17: POST /orders avec corps invalide | E17: Vérifier la validation des entrées API | F17: Clé API configurée | G17: Corps vide ; JSON cassé ; items absent ; items = [] ; quantity = "deux" ; product_id inexistant ; payment_method = "bitcoin" ; items de deux restaurants différents | H17: 1. Envoyer chaque corps 2. Relever code et message 3. Vérifier qu'aucune commande n'a été créée (GET /orders) | I17: 400 attendu (OpenAPI) avec le champ fautif identifié ; jamais 500 ni 201 ; aucune commande créée ; panier multi-restaurants refusé (l'appli est mono-restaurant) | J17: R5 | L17: Skipped | O17: 12/10/2026 — Samy
A18: ERR-05 | B18: Erreur | C18: UI+API | D18: Commande avec panier vide | E18: Vérifier que la commande vide est impossible | F18: Connecté en alice ; panier vide | G18: UI : panier vide ; API : items = [] | H18: 1. Aller au panier vide, tenter de lancer le checkout (bouton, URL directe) 2. POST /orders avec items = [] | I18: Refus avec message ; aucune commande créée dans les deux cas | J18: R3 | L18: Skipped | O18: 12/10/2026 — Samy
A19: ERR-06 | B19: Erreur | C19: UI+API | D19: Saisie hostile dans les champs texte et paramètres | E19: Vérifier l'échappement des entrées (vérification de base) | F19: Champs texte accessibles (connexion, recherche, éventuel commentaire) | G19: <script>alert(1)</script> ; ' OR 1=1-- ; <b>gras</b> ; ?q=' OR 1=1-- sur /api/restaurants | H19: 1. Saisir chaque chaîne dans les champs de l'UI 2. Appeler GET /api/restaurants?q=<chaîne> 3. Relire là où le texte réapparaît | I19: Texte affiché littéralement, aucun script exécuté, aucune erreur 500, aucun résultat inattendu | J19: R7 | L19: Skipped | O19: 12/10/2026 — Samy
A20: REG-01 | B20: Règle métier | C20: UI+API | D20: Coupon WELCOME10 valide | E20: Vérifier la réduction et son application à la commande | F20: Panier ≥ minimum du coupon ; connecté en alice | G20: Code WELCOME10 ; subtotal 32.50 (exemple de la doc) | H20: 1. POST /coupons/validate {"code":"WELCOME10","subtotal":32.50} 2. POST /orders avec "coupon":"WELCOME10" 3. Comparer la réduction avec un calcul manuel 4. Vérifier dans l'UI | I20: Réduction conforme à la règle, appliquée une seule fois, identique entre validate, commande et UI | J20: R4 | L20: Skipped | O20: 12/10/2026 — Samy
A21: REG-02 | B21: Règle métier | C21: API | D21: Coupon expiré, inconnu, minimum non atteint, réutilisé | E21: Vérifier le refus des coupons invalides | F21: Coupon expiré [code à trouver dans l'UI / la base de démo] ; panier sous le minimum | G21: Code expiré [à relever] ; code inventé ; WELCOME10 sous le minimum ; WELCOME10 réutilisé ; casse (welcome10) | H21: 1. POST /coupons/validate pour chaque cas 2. Tenter la création de commande avec ces codes 3. Comparer validate et orders | I21: Coupon inexistant ou expiré : 404 (OpenAPI). Minimum non atteint : relever le code (200 « traité » ? 400 ?) et lire le corps pour voir s'il dit clairement que le coupon n'est pas appliqué. Pas de double réduction ; même règle dans validate et dans orders | J21: R4 | L21: Skipped | O21: 12/10/2026 — Samy
A22: REG-03 | B22: Règle métier | C22: UI+API | D22: Frais de livraison et seuil de gratuité | E22: Vérifier le calcul des frais | F22: Règle des frais lue dans l'UI ou la réponse API [à confirmer] | G22: Paniers sous / à / au-dessus du seuil éventuel de gratuité | H22: 1. Construire chaque panier 2. Relever les frais (UI et réponse API) 3. Comparer au calcul attendu | I22: Frais conformes à la règle à chaque borne, inclus dans le total final, identiques UI et API | J22: R10 | L22: Skipped | O22: 12/10/2026 — Samy
A23: REG-04 | B23: Règle métier | C23: UI+API | D23: Restaurant fermé ou produit hors stock non commandable | E23: Vérifier que l'indisponible n'est pas commandable | F23: Un restaurant avec is_open = false et un produit indisponible repérés via GET /api/restaurants et /products | G23: Restaurant fermé ; produit hors stock | H23: 1. Tenter d'ajouter l'article dans l'UI 2. POST /orders sur ce restaurant / ce produit 3. Comparer UI et API | I23: Restaurant fermé ou produit indisponible : refus dans l'UI et dans l'API (409 documenté pour produit indisponible) ; message clair ; aucune commande créée | J23: R8 | L23: Skipped | O23: 12/10/2026 — Samy
A24: REG-05 | B24: Règle métier | C24: API | D24: Annulation selon le statut + commande d'un autre utilisateur | E24: Vérifier la règle d'annulation et l'isolation entre comptes | F24: Commandes à différents statuts ; une commande de bob [à créer en UI avec bob] | G24: POST /api/orders/{id}/cancel : commande récente, commande avancée, déjà annulée, commande de bob avec la clé d'alice | H24: 1. Annuler une commande récente 2. Annuler une commande avancée 3. Annuler deux fois 4. Annuler la commande de bob avec la clé d'alice 5. GET /orders : le statut est à jour ? | I24: Annulation OK au début (200) ; annulation impossible : 409 (OpenAPI) avec message ; commande de bob : 403 attendu (documenté sur GET /orders/{id} ; relever le code sur cancel) ; statut mis à jour partout | J24: R6 | L24: Skipped | O24: 12/10/2026 — Samy
A25: REG-06 | B25: Règle métier | C25: UI+API | D25: Même montant à tous les endroits | E25: Vérifier la cohérence panier ↔ confirmation ↔ historique ↔ API | F25: Une commande avec WELCOME10 et frais passée (cas NOM-04 / REG-01) | G25: La commande ci-dessus | H25: 1. Noter le montant du panier 2. Celui de la confirmation 3. Celui de l'historique UI 4. Celui de GET /api/orders/{id} 5. Idem pour la réduction et les frais | I25: Sous-total, réduction, frais et total identiques aux quatre endroits | J25: R9 | K25: je n'ai pas réussi je crois monsieur mdrr | L25: Skipped | O25: 12/10/2026 — Samy

Sheet Synthèse
A1: Synthèse de campagne
A3: Cas prévus | B3: =COUNTA('Cas de test'!A2:A25) -> 24
A4: À exécuter | B4: =COUNTIF('Cas de test'!L2:L25,"À exécuter") -> 0
A5: Pass | B5: =COUNTIF('Cas de test'!L2:L25,"Pass") -> 0
A6: Fail | B6: =COUNTIF('Cas de test'!L2:L25,"Fail") -> 0
A7: Blocked | B7: =COUNTIF('Cas de test'!L2:L25,"Blocked") -> 0
A8: Skipped | B8: =COUNTIF('Cas de test'!L2:L25,"Skipped") -> 24
A9: Exécutés (Pass + Fail) | B9: =B5+B6 -> 0
A10: Avancement (cas hors « À exécuter ») | B10: =IFERROR((B3-B4)/B3,0) -> 1
A11: Taux de réussite (Pass / exécutés) | B11: =IFERROR(B5/B9,"n/a") -> n/a
A12: Contrôle : somme des statuts = cas prévus | B12: =IF(B4+B5+B6+B7+B8=B3,"OK","ÉCART") -> OK
A14: Par catégorie
A15: Catégorie | B15: Cas | C15: Pass | D15: Fail | E15: Blocked | F15: Skipped
A16: Nominal | B16: =COUNTIF('Cas de test'!B2:B25,A16) -> 6 | C16: =COUNTIFS('Cas de test'!B2:B25,$A16,'Cas de test'!L2:L25,"Pass") -> 0 | D16: =COUNTIFS('Cas de test'!B2:B25,$A16,'Cas de test'!L2:L25,"Fail") -> 0 | E16: =COUNTIFS('Cas de test'!B2:B25,$A16,'Cas de test'!L2:L25,"Blocked") -> 0 | F16: =COUNTIFS('Cas de test'!B2:B25,$A16,'Cas de test'!L2:L25,"Skipped") -> 6
A17: Limite | B17: =COUNTIF('Cas de test'!B2:B25,A17) -> 6 | C17: =COUNTIFS('Cas de test'!B2:B25,$A17,'Cas de test'!L2:L25,"Pass") -> 0 | D17: =COUNTIFS('Cas de test'!B2:B25,$A17,'Cas de test'!L2:L25,"Fail") -> 0 | E17: =COUNTIFS('Cas de test'!B2:B25,$A17,'Cas de test'!L2:L25,"Blocked") -> 0 | F17: =COUNTIFS('Cas de test'!B2:B25,$A17,'Cas de test'!L2:L25,"Skipped") -> 6
A18: Erreur | B18: =COUNTIF('Cas de test'!B2:B25,A18) -> 6 | C18: =COUNTIFS('Cas de test'!B2:B25,$A18,'Cas de test'!L2:L25,"Pass") -> 0 | D18: =COUNTIFS('Cas de test'!B2:B25,$A18,'Cas de test'!L2:L25,"Fail") -> 0 | E18: =COUNTIFS('Cas de test'!B2:B25,$A18,'Cas de test'!L2:L25,"Blocked") -> 0 | F18: =COUNTIFS('Cas de test'!B2:B25,$A18,'Cas de test'!L2:L25,"Skipped") -> 6
A19: Règle métier | B19: =COUNTIF('Cas de test'!B2:B25,A19) -> 6 | C19: =COUNTIFS('Cas de test'!B2:B25,$A19,'Cas de test'!L2:L25,"Pass") -> 0 | D19: =COUNTIFS('Cas de test'!B2:B25,$A19,'Cas de test'!L2:L25,"Fail") -> 0 | E19: =COUNTIFS('Cas de test'!B2:B25,$A19,'Cas de test'!L2:L25,"Blocked") -> 0 | F19: =COUNTIFS('Cas de test'!B2:B25,$A19,'Cas de test'!L2:L25,"Skipped") -> 6
A20: Total | B20: =SUM(B16:B19) -> 24 | C20: =SUM(C16:C19) -> 0 | D20: =SUM(D16:D19) -> 0 | E20: =SUM(E16:E19) -> 0 | F20: =SUM(F16:F19) -> 24
A22: Aide à la décision Go / No-Go
A23: Bugs 🔥 Cramé ouverts (à saisir) | B23: 0
A24: Bugs 🥵 Brûlé ouverts (à saisir) | B24: 0
A25: Parcours P1/P2 en échec ? (1 = oui, 0 = non) | B25: 0
A26: Verdict automatique | B26: =IF(B9=0,"AUCUN CAS EXÉCUTÉ",IF(B4>0,"CAMPAGNE INCOMPLÈTE",IF(OR(B23>0,B25=1),"NO-GO",IF(B24>0,"GO SOUS CONDITIONS","GO")))) -> AUCUN CAS EXÉCUTÉ
A28: Hypothèses : règles de décision = celles de test-strategy.md §9 (choix de Samy, pas du brief). Le verdict est une aide ; la recommandation argumentée est dans execution-report.md.
